Metadata-Version: 1.1
Name: galapagos
Version: 1.0.0.dev1
Summary: An extendable genetic algorithm frame work (coming soon)
Home-page: https://github.com/kosieram21/Galapagos.git
Author: Shane Kosieradzki, Mitch Kosieradzki
Author-email: galapagos.devs@gamil.com
License: UNKNOWN
Platform: UNKNOWN
Classifier: License :: OSI Approved :: MIT License
Classifier: Natural Language :: English
Classifier: Operating System :: POSIX
Classifier: Programming Language :: Python :: 3 :: Only
Classifier: Programming Language :: Python :: Implementation :: CPython
Classifier: Topic :: Scientific/Engineering
Classifier: Topic :: Software Development :: Libraries
